metaflow_extensions/dbt_ext/cmd/dbt_cmd.py
metaflow_extensions/dbt_ext/cmd/flow_generator.py
metaflow_extensions/dbt_ext/cmd/mfextinit_dbt_ext.py
metaflow_extensions/dbt_ext/config/mfextinit_dbt_ext.py
metaflow_extensions/dbt_ext/plugins/mfextinit_dbt_ext.py
metaflow_extensions/dbt_ext/plugins/cards/dbt_docs/__init__.py
metaflow_extensions/dbt_ext/plugins/dbt/__init__.py
metaflow_extensions/dbt_ext/plugins/dbt/dbt_decorator.py
metaflow_extensions/dbt_ext/plugins/dbt/dbt_executor.py
metaflow_extensions/dbt_ext/toplevel/mfextinit_dbt_ext.py
metaflow_extensions/dbt_ext/toplevel/toplevel.py
metaflow_dbt_extension-1.0.0.dist-info/LICENSE
metaflow_dbt_extension-1.0.0.dist-info/METADATA
metaflow_dbt_extension-1.0.0.dist-info/WHEEL
metaflow_dbt_extension-1.0.0.dist-info/top_level.txt
metaflow_dbt_extension-1.0.0.dist-info/RECORD
